[
      {
        "image_url": "https://upload.wikimedia.org/wikipedia/commons/f/fb/Texas_longhorn.jpg",
        "title": "Longhorn",
        "description": "This is a Longhorn.",
        "horns": 2
      },
      {
        "image_url": "https://upload.wikimedia.org/wikipedia/commons/8/82/White_Baby_Rhino.jpg",
        "title": "Rhino",
        "description": "This is a Rhino which is a big dangerous horned animal.",
        "horns": 1
      },
      {
        "image_url": "https://upload.wikimedia.org/wikipedia/commons/3/34/Serengeti_Impala3.jpg",
        "title": "Impala",
        "description": "This is a impala.",
        "keyword": "unicorn", 
        "horns": 2
      }

]